sql_guard-0.0.3.dist-info/licenses/LICENSE
sqlguard/__init__.py
sqlguard/translators/PanderaMapping.py
sqlguard/translators/SchemaParsers.py
sqlguard/translators/__init__.py
sqlguard/utils/SQLHelpers.py
sqlguard/utils/__init__.py
sqlguard/validator/CheckBase.py
sqlguard/validator/CheckImplementations.py
sqlguard/validator/SQLValidator.py
sqlguard/validator/__init__.py
sql_guard-0.0.3.dist-info/METADATA
sql_guard-0.0.3.dist-info/WHEEL
sql_guard-0.0.3.dist-info/top_level.txt
sql_guard-0.0.3.dist-info/RECORD
