Metadata-Version: 2.4
Name: sql-guard
Version: 0.0.3
Summary: A small package for data quality rules using SQL
Author-email: Ygor Jesus <ygorj.skat@gmail.com>
License-Expression: MIT
Project-URL: Homepage, https://github.com/Ygor-J/sql-guard
Project-URL: Issues, https://github.com/Ygor-J/sql-guard/issues
Classifier: Programming Language :: Python :: 3
Classifier: Operating System :: OS Independent
Requires-Python: >=3.8
License-File: LICENSE
Dynamic: license-file
